MANIFEST.in
README
setup.py
nodel/__init__.py
nodel/functions.py
nodel/nodel_core.py
nodel.egg-info/PKG-INFO
nodel.egg-info/SOURCES.txt
nodel.egg-info/dependency_links.txt
nodel.egg-info/requires.txt
nodel.egg-info/top_level.txt
nodel/framework/__init__.py
nodel/framework/common.py
nodel/framework/modules.py
nodel/framework/django_1_11_3/__init__.py
nodel/framework/django_1_11_3/config_base.py
nodel/framework/django_1_11_3/config_dev.py
nodel/framework/django_1_11_3/config_prod.py
nodel/framework/django_1_11_3/manage.py
nodel/framework/django_1_11_3/urls.py
nodel/framework/django_1_11_3/wsgi.py