Metadata-Version: 1.1
Name: nodel
Version: 0.3.3
Summary: django project manager
Home-page: https://github.com/ary4n/nodel
Author: aryan
Author-email: alikhaniaryan@live.com
License: MIT
Download-URL: https://github.com/ary4n/nodel/archive/0.3.3.tar.gz
Keywords: minimal django project manager
Platform: UNKNOWN
